CHANGES.rst
LICENSE.txt
MANIFEST.in
README.rst
setup.py
djangorecipebook/__init__.py
djangorecipebook/exceptions.py
djangorecipebook/helpers.py
djangorecipebook/templating.py
djangorecipebook/version.py
djangorecipebook.egg-info/PKG-INFO
djangorecipebook.egg-info/SOURCES.txt
djangorecipebook.egg-info/dependency_links.txt
djangorecipebook.egg-info/entry_points.txt
djangorecipebook.egg-info/not-zip-safe
djangorecipebook.egg-info/requires.txt
djangorecipebook.egg-info/top_level.txt
djangorecipebook/recipes/__init__.py
djangorecipebook/recipes/base.py
djangorecipebook/recipes/create.py
djangorecipebook/recipes/gunicorn.py
djangorecipebook/recipes/makemigrations.py
djangorecipebook/recipes/manage.py
djangorecipebook/recipes/migrate.py
djangorecipebook/recipes/test.py
djangorecipebook/recipes/wsgi.py
djangorecipebook/scripts/__init__.py
djangorecipebook/scripts/fcgi.py
djangorecipebook/scripts/gunicorn.py
djangorecipebook/scripts/makemigrations.py
djangorecipebook/scripts/manage.py
djangorecipebook/scripts/pytest.py
djangorecipebook/scripts/wsgi.py