Metadata-Version: 2.1
Name: djangorecipebook
Version: 1.5
Summary: Buildout recipes for django development
Home-page: https://bitbucket.org/tkhyn/djangorecipebook/
Author: Thomas Khyn
Author-email: thomas@ksytek.com
License: UNKNOWN
Keywords: django,buildout,recipe
Platform: UNKNOWN
Classifier: Programming Language :: Python
Classifier: Programming Language :: Python :: 3
Classifier: License :: OSI Approved :: MIT License
Classifier: Operating System :: OS Independent
Classifier: Development Status :: 5 - Production/Stable
Classifier: Intended Audience :: Developers
Classifier: Framework :: Buildout :: Recipe
Classifier: Framework :: Django
Classifier: Topic :: Software Development :: Build Tools
Provides-Extra: nose
Provides-Extra: pytest
Provides-Extra: gunicorn
